{
    "missions": [
        {
            "missionId": 0,
            "missionText": "Dump or don't dump?",
            "missionName": "Poop",
            "options": [
                {
                    "optionsText": "Yes",
                    "_missionId": 1
                },
                {
                    "optionsText": "No",
                    "_missionId": 2
                }
            ]
        },
        {
            "missionId": 1,
            "missionText": "Dump1 or don't dump1?",
            "missionName": "Poop1",
            "options": [
                {
                    "optionsText": "Yes",
                    "_missionId": 2
                },
                {
                    "optionsText": "No",
                    "_missionId": 3
                }
            ]
        }
    ]
}